eurydice/CV.py
eurydice/__init__.py
eurydice/input.py
eurydice/kepler.py
eurydice/kernel.py
eurydice/plot.py
eurydice-0.5.post1.dist-info/licenses/LICENSE
eurydice-0.5.post1.dist-info/METADATA
eurydice-0.5.post1.dist-info/WHEEL
eurydice-0.5.post1.dist-info/top_level.txt
eurydice-0.5.post1.dist-info/RECORD
