Metadata-Version: 2.4
Name: eurydice
Version: 0.5.post1
Summary: A package for evaluating radial velocity signal models using cross-validation methods and Gaussian processes.
Author-email: Kaylee Barrera <kaybarr4@gmail.com>
Classifier: Programming Language :: Python :: 3
Classifier: License :: OSI Approved :: MIT License
Classifier: Operating System :: OS Independent
Classifier: Intended Audience :: Science/Research
Classifier: Topic :: Scientific/Engineering :: Astronomy
Requires-Python: >=3.8
License-File: LICENSE
Requires-Dist: numpy
Requires-Dist: scipy
Requires-Dist: matplotlib
Requires-Dist: pandas
Dynamic: license-file
